flag_register.v
module flag_register(
    input clk, reset,
    input update,
    input zero_in, negative_in, carry_in, overflow_in,
    output reg zero, negative, carry, overflow 
);

    always @(posedge clk or posedge reset) begin
        if(reset) begin
            zero <= 0;
            negative <= 0;
            carry <= 0;
            overflow <= 0;
        end
        else if(update) begin
            zero <= zero_in;
            negative <= negative_in;
            carry <= carry_in;
            overflow <= overflow_in;
        end
    end
endmodule

alu_4bit.v
module alu_4bit(
    input [3:0] a, b,
    input [3:0] opcode,
    input enable,
    output reg [3:0] ALU_out,
    output reg zero,negative,carry,overflow
);

    reg [4:0] temp;
    parameter   ADD = 4'b0000,
                SUB = 4'b0001,
                INCA= 4'b0010,
                DECA= 4'b0011,
                AND = 4'b0100,
                OR  = 4'b0101,
                XOR = 4'b0110,
                NOT = 4'b0111,
                SLL = 4'b1000,
                SRL = 4'b1001,
                SRA = 4'b1010;

    always @(*) begin
        temp = 0;
        ALU_out = 0;
        carry = 0;
        zero = 0;
        negative = 0;
        if(enable) begin
            case(opcode)
                ADD: begin
                    temp = a + b;
                    ALU_out = temp[3:0];
                    carry = temp[4];
                    overflow = (a[3] == b[3]) && (ALU_out[3] != a[3]);
                end
                SUB: begin
                    temp = a - b;
                    ALU_out = temp[3:0];
                    carry = (a>=b);
                    overflow = (a[3] != b[3]) && (ALU_out[3] != a[3]);
                end
                INCA: begin
                    temp = a + 1; 
                    ALU_out = temp[3:0];
                    carry = temp[4];
                    overflow = (a == 4'b0111);
                end
                DECA: begin
                    temp = a - 1;
                    ALU_out = temp[3:0];
                    carry = (a >= 1);
                    overflow = (a == 4'b1000);
                end

                AND: ALU_out = a & b;
                OR: ALU_out = a | b;
                XOR: ALU_out = a ^ b;
                NOT: ALU_out = ~a;

                SLL: begin
                    ALU_out = a << 1;
                    carry = a[3];
                end
                SRL: begin
                    ALU_out = a >> 1;
                    carry = a[0];
                end
                SRA: begin
                    ALU_out = {a[3],a[3:1]};
                    carry = a[0];
                end            
                default: ALU_out = 4'b0000;
            endcase
        end
        zero = (ALU_out == 0);
        negative = ALU_out[3];
    end

endmodule

alu_4bit_tb.v
`timescale 1ns/1ns
`include "alu_4bit.v"
`include "flag_register.v"

module alu_4bit_tb;

    reg [3:0] a, b, opcode;
    wire [3:0] ALU_out;
    wire zero_i, negative_i, carry_i, overflow_i;
    wire zero, negative, carry, overflow;
    reg clk, reset, update, enable;

    alu_4bit DUT(.a(a), .b(b), .opcode(opcode), .enable(enable), .ALU_out(ALU_out), .zero(zero_i), 
                .negative(negative_i), .carry(carry_i), .overflow(overflow_i));


    flag_register FR_inst(.clk(clk), .reset(reset), .update(update),
                         .zero_in(zero_i), .negative_in(negative_i), .carry_in(carry_i), .overflow_in(overflow_i),
                        .zero(zero), .negative(negative), .carry(carry), .overflow(overflow));
                        
    always #5 clk = ~clk;

    initial begin
        $dumpfile("alu_4bit.vcd");
        $dumpvars(0, alu_4bit_tb);

        clk = 0; reset = 1; update = 0; enable = 0;
        #10 reset = 0;

        // ADD
        a = 4'b0011; b = 4'b0100; opcode = 4'b0000;
        enable = 1; update = 1; #10; update = 0;
        $display("ADD: %d + %d = %d | Z=%b N=%b C=%b V=%b", a, b, ALU_out, zero, negative, carry, overflow);

        // SUB
        a = 4'b0101; b = 4'b0011; opcode = 4'b0001;
        update = 1; #10; update = 0;
        $display("SUB: %d - %d = %d | Z=%b N=%b C=%b V=%b", a, b, ALU_out, zero, negative, carry, overflow);

        // AND
        a = 4'b1100; b = 4'b1010; opcode = 4'b0100;
        update = 1; #10; update = 0;
        $display("AND: %b & %b = %b", a, b, ALU_out);

        // OR
        a = 4'b1100; b = 4'b1010; opcode = 4'b0101;
        update = 1; #10; update = 0;
        $display("OR: %b | %b = %b", a, b, ALU_out);

        // SLL
        a = 4'b1001; b = 4'b0000; opcode = 4'b1000;
        update = 1; #10; update = 0;
        $display("SLL: %b << 1 = %b", a, ALU_out);

        // SRL
        a = 4'b1001; b = 4'b0000; opcode = 4'b1001;
        update = 1; #10; update = 0;
        $display("SRL: %b >> 1 = %b", a, ALU_out);

        // SRA
        a = 4'b1001; b = 4'b0000; opcode = 4'b1010;
        update = 1; #10; update = 0;
        $display("SRA: %b >>> 1 = %b", a, ALU_out);

        $finish;
    end

endmodule

alu_4bit.vcd
$date
	Thu Jul 24 20:11:47 2025
$end
$version
	Icarus Verilog
$end
$timescale
	1ns
$end
$scope module alu_4bit_tb $end
$var wire 1 ! zero_i $end
$var wire 1 " zero $end
$var wire 1 # overflow_i $end
$var wire 1 $ overflow $end
$var wire 1 % negative_i $end
$var wire 1 & negative $end
$var wire 1 ' carry_i $end
$var wire 1 ( carry $end
$var wire 4 ) ALU_out [3:0] $end
$var reg 4 * a [3:0] $end
$var reg 4 + b [3:0] $end
$var reg 1 , clk $end
$var reg 1 - enable $end
$var reg 4 . opcode [3:0] $end
$var reg 1 / reset $end
$var reg 1 0 update $end
$scope module DUT $end
$var wire 4 1 a [3:0] $end
$var wire 4 2 b [3:0] $end
$var wire 1 - enable $end
$var wire 4 3 opcode [3:0] $end
$var parameter 4 4 ADD $end
$var parameter 4 5 AND $end
$var parameter 4 6 DECA $end
$var parameter 4 7 INCA $end
$var parameter 4 8 NOT $end
$var parameter 4 9 OR $end
$var parameter 4 : SLL $end
$var parameter 4 ; SRA $end
$var parameter 4 < SRL $end
$var parameter 4 = SUB $end
$var parameter 4 > XOR $end
$var reg 4 ? ALU_out [3:0] $end
$var reg 1 ' carry $end
$var reg 1 % negative $end
$var reg 1 # overflow $end
$var reg 5 @ temp [4:0] $end
$var reg 1 ! zero $end
$upscope $end
$scope module FR_inst $end
$var wire 1 ' carry_in $end
$var wire 1 , clk $end
$var wire 1 % negative_in $end
$var wire 1 # overflow_in $end
$var wire 1 / reset $end
$var wire 1 0 update $end
$var wire 1 ! zero_in $end
$var reg 1 ( carry $end
$var reg 1 & negative $end
$var reg 1 $ overflow $end
$var reg 1 " zero $end
$upscope $end
$upscope $end
$enddefinitions $end
$comment Show the parameter values. $end
$dumpall
b110 >
b1 =
b1001 <
b1010 ;
b1000 :
b101 9
b111 8
b10 7
b11 6
b100 5
b0 4
$end
#0
$dumpvars
b0 @
b0 ?
bx 3
bx 2
bx 1
00
1/
bx .
0-
0,
bx +
bx *
b0 )
0(
0'
0&
0%
0$
x#
0"
1!
$end
#5
1,
#10
0#
b111 )
b111 ?
b111 @
0!
0,
10
1-
b0 .
b0 3
b100 +
b100 2
b11 *
b11 1
0/
#15
1,
#20
1'
b10 )
b10 ?
b10 @
0,
b1 .
b1 3
b11 +
b11 2
b101 *
b101 1
10
#25
1(
1,
#30
1%
0'
b1000 )
b1000 ?
b0 @
0,
b100 .
b100 3
b1010 +
b1010 2
b1100 *
b1100 1
10
#35
0(
1&
1,
#40
1%
b1110 )
b1110 ?
0,
b101 .
b101 3
10
#45
1,
#50
1'
0%
b10 )
b10 ?
0,
b1000 .
b1000 3
b0 +
b0 2
b1001 *
b1001 1
10
#55
1(
0&
1,
#60
1'
b100 )
b100 ?
0,
b1001 .
b1001 3
10
#65
1,
#70
1%
1'
b1100 )
b1100 ?
0,
b1010 .
b1010 3
10
#75
1&
1,
#80
0,
00
